polymarket_trade_executor/__init__.py
polymarket_trade_executor/executor.py
polymarket_trade_executor-0.1.1.dist-info/METADATA
polymarket_trade_executor-0.1.1.dist-info/WHEEL
polymarket_trade_executor-0.1.1.dist-info/licenses/LICENSE
polymarket_trade_executor-0.1.1.dist-info/RECORD
