Metadata-Version: 2.4
Name: polymarket-trade-executor
Version: 0.1.1
Summary: Trade executor for Polymarket CLOB API - supports orders, split, merge, redeem
Project-URL: Homepage, https://github.com/yourname/polymarket-trade-executor
Project-URL: Repository, https://github.com/yourname/polymarket-trade-executor
Author-email: Your Name <your@email.com>
License-Expression: MIT
License-File: LICENSE
Keywords: clob,crypto,polymarket,prediction-market,trading
Classifier: Development Status :: 4 - Beta
Classifier: Intended Audience :: Developers
Classifier: License :: OSI Approved :: MIT License
Classifier: Programming Language :: Python :: 3
Classifier: Programming Language :: Python :: 3.10
Classifier: Programming Language :: Python :: 3.11
Classifier: Programming Language :: Python :: 3.12
Classifier: Topic :: Office/Business :: Financial :: Investment
Requires-Python: >=3.10
Requires-Dist: eth-abi>=5.0.0
Requires-Dist: eth-utils>=4.0.0
Requires-Dist: httpx>=0.27.0
Requires-Dist: py-clob-client>=0.18.0
Requires-Dist: py-order-utils>=0.3.0
Provides-Extra: dev
Requires-Dist: pytest-asyncio>=0.23.0; extra == 'dev'
Requires-Dist: pytest>=8.0.0; extra == 'dev'
Requires-Dist: python-dotenv>=1.0.0; extra == 'dev'
Provides-Extra: relayer
Requires-Dist: py-builder-relayer-client>=0.0.1; extra == 'relayer'
Requires-Dist: py-builder-signing-sdk>=0.0.1; extra == 'relayer'
